{
  "type": "Feature",
  "properties": {
    "iso:country":"ZA",
    "sg:address":"27 Plumer Road Woodstock",
    "sg:city":"Cape Town",
    "sg:classifiers":[
        {
            "category":"Manufacturing",
            "subcategory":"Electronics",
            "type":"Manufacturing & Wholesale Goods"
        }
    ],
    "sg:postcode":"8000",
    "sg:tags":[
        "tourism",
        "tour-operator",
        "independent-travellers",
        "audio-guide",
        "hire-cars",
        "broadcast",
        "spain",
        "new-zealand",
        "south-africa",
        "hawaii",
        "northern-ireland",
        "history",
        "culture",
        "music",
        "intellipoint-system"
    ],
    "sg:website":"http://www.tourismradio.co.za",
    "wof:name":"Tourism Radio",
    "wof:placetype":"venue"
},
  "geometry": {"coordinates":[18.45045,-33.93155],"type":"Point"}
}